{
  "games": [
    {
      "name": "Geometry Dash",
      "user_id": "Dalmanski GD",
      "category": [
        "Rhythm",
        "Paid"
      ],
      "description": "This is my first and favorite game ever. Go to my Dalmanski GD on YT channel.",
      "icon": "https://play-lh.googleusercontent.com/ixHXzBWPmmKWIBxDMfjbIXK10UQCTDvIYOcs_uLXHCRbdsz2siJFYfb7MqckU8eC3Ks"
    },
    {
      "name": "Mobile Legends: Bang Bang",
      "user_id": "295211318 (3589)",
      "category": "",
      "description": "My favorite hero is Hanzo",
      "icon": "https://play-lh.googleusercontent.com/NiIHdrOS85r76ggTpn1uLxslWAfmvi1WVVQY5Enrj3ZAcVBcb11RkkTFbej8qxB9UK0JPDhRVajVz_ogmqiC"
    },
    {
      "name": "Call of Duty®: Mobile - Garena",
      "user_id": "6818033742175535105",
      "category": "",
      "description": "No description provided",
      "icon": "https://play-lh.googleusercontent.com/0DENLOaGXbadNpuWBLJf4lEhJCJmQV5Na1k5L311-sDPSncoW6_kDLsG_Vc4N0_AM_IGEf3cKTHGHKAyBYAe"
    },
    {
      "name": "Punishing: Gray Raven",
      "user_id": "12834324",
      "category": "Gacha",
      "description": "No description provided",
      "icon": "https://play-lh.googleusercontent.com/YWC3LT98lQ2INdjSE-zEEorezgBedT0N5G1lc8QEX-qpUqqJ2zOEnFOSWYQp8NBGwpo6Yp3HAgkwU8fWBW24DA"
    },
    {
      "name": "Honkai: Star Rail",
      "user_id": "825016080",
      "category": "Gacha",
      "description": "The beautiful artwork and best animation Gacha Game I've ever played!",
      "icon": "https://play-lh.googleusercontent.com/IqXUfiwbK-NCu5KyyK9P3po1kd4ZPOC4QJVWRk2ooJXnUcSpkCUQRYYJ-9vZkCEnPOxDIEWjNpS30OwHNZTtCKw",
      "my_gm_rec_img": "/My_Info/Game_Info/My-HSR-Info.png",
      "my_gm_rec_link": "https://act.hoyolab.com/app/community-game-records-sea/rpg/index.html?bbs_presentation_style=fullscreen&gid=6&user_id=71410534&utm_source=share&utm_medium=link&bbs_theme=dark&bbs_theme_device=1&utm_campaign=web#/hsr"
    },
    {
      "name": "Genshin Impact",
      "user_id": "831226193",
      "category": "Gacha",
      "description": "No description provided",
      "icon": "https://play-lh.googleusercontent.com/YQqyKaXX-63krqsfIzUEJWUWLINxcb5tbS6QVySdxbS7eZV7YB2dUjUvX27xA0TIGtfxQ5v-tQjwlT5tTB-O"
    },
    {
      "name": "Farlight 84",
      "user_id": "Jaymantrix#18552211",
      "category": "",
      "description": "No description provided",
      "icon": "https://encrypted-tbn0.gstatic.com/images?q=tbn:ANd9GcSnKU99vKGAWbKq4wYr6yA2iLYtVlwIjZuhGA&s"
    },
    {
      "name": "Tower of Fantasy",
      "user_id": "16013236078",
      "category": "Gacha",
      "description": "No description provided",
      "icon": "https://encrypted-tbn0.gstatic.com/images?q=tbn:ANd9GcTb7U6oFdB56nOAFl36Lh-02fEYlkon4IXueg&s"
    },
    {
      "name": "Snowbreak: Containment Zone",
      "user_id": "11843366",
      "category": "Gacha",
      "description": "This FB acc is gone. No new account provided.",
      "icon": "https://play-lh.googleusercontent.com/rzvj2FaKgGNlLOjMPl0DVXX5uL9ash2u_2JZu_eAmYcleMrw4Hgecla1dF8XRw5rgfY"
    },
    {
      "name": "Arknights",
      "user_id": "23319936",
      "category": "Gacha",
      "description": "No description provided",
      "icon": "https://encrypted-tbn0.gstatic.com/images?q=tbn:ANd9GcTpFdb4n2aXPTyvJDJbyqYztn4Mbgg6q3qFow&s"
    },
    {
      "name": "Dota 2",
      "user_id": "920274306",
      "category": "",
      "description": "No description provided",
      "icon": "https://encrypted-tbn0.gstatic.com/images?q=tbn:ANd9GcTQGirSmTuO9ULV1xLFPAGWsdCL9cIdGR9Cng&s"
    },
    {
      "name": "OSU",
      "user_id": "13831735",
      "category": "Rhythm",
      "description": "No description provided",
      "icon": "https://th.bing.com/th/id/OIP.5f9M-P9kn72IQs1-IxCDpAHaHa?cb=thvnextc1&rs=1&pid=ImgDetMain"
    },
    {
      "name": "Clash of Clans",
      "user_id": "#QRCCGQQQQ",
      "category": "",
      "description": "No description provided",
      "icon": "https://encrypted-tbn0.gstatic.com/images?q=tbn:ANd9GcQwrSEDIvOOBUZMc7rsno-D2H3NvCXjaX6c_A&s"
    },
    {
      "name": "Clash Royale",
      "user_id": "#9V8VVJ0CQ",
      "category": "",
      "description": "No description provided",
      "icon": "https://encrypted-tbn0.gstatic.com/images?q=tbn:ANd9GcQMt18VVv2_bw1FRALdGOsPqf027hhFfQVFzQ&s"
    },
    {
      "name": "Epic Seven",
      "user_id": "930090237",
      "category": "Gacha",
      "description": "No description provided",
      "icon": "https://encrypted-tbn0.gstatic.com/images?q=tbn:ANd9GcQIQH9CaJicaWubiQL1n1bAofA5OHX3vSqKuA&s"
    },
    {
      "name": "Blue Archive",
      "user_id": "7820880",
      "category": "Gacha",
      "description": "No description provided",
      "icon": "https://encrypted-tbn0.gstatic.com/images?q=tbn:ANd9GcQZdjBzBfWDzrAzwuxyl5hp0E_mzV10-oI-dQ&s"
    },
    {
      "name": "Reverse: 1999",
      "user_id": "401106772",
      "category": "Gacha",
      "description": "No description provided",
      "icon": "https://play-lh.googleusercontent.com/Hg_u1BVutZU840xpTuahpCRraRDjg7egdDsXWNqhSqxRxEgWSu3_uD4F-xihX64ysFU"
    },
    {
      "name": "Warframe",
      "user_id": "Jaymantrix#171",
      "category": "",
      "description": "No description provided",
      "icon": "https://encrypted-tbn0.gstatic.com/images?q=tbn:ANd9GcR_SpXiXKEsN5HaKvVrN2T89OdzSglE5ffeCQ&s"
    },
    {
      "name": "Azur Lane",
      "user_id": "409945230",
      "category": "Gacha",
      "description": "No description provided",
      "icon": "https://play-lh.googleusercontent.com/Xvzm9AdC2rEpP_gcwoJWBD7BsDClyOhRZ5AmIyhZDKRRCB2k1hdovUqpLgEIcx5b1YY"
    },
    {
      "name": "Asphalt 9 Legends",
      "user_id": "w-936140",
      "category": "",
      "description": "No description provided",
      "icon": "https://encrypted-tbn0.gstatic.com/images?q=tbn:ANd9GcRSWfjSqGdrvPwcg0_k3bTcS0jivnxrerjk0A&s"
    },
    {
      "name": "Aether Gazer",
      "user_id": "53688814900",
      "category": "Gacha",
      "description": "No description provided",
      "icon": "https://play-lh.googleusercontent.com/_q1Ba4Vs6NGWBSx997t6BYyfkVbsEynsktMBl4xkUOWN66mxKuWHClA5B47t8st1XsM"
    },
    {
      "name": "GODDESS OF VICTORY: NIKKE",
      "user_id": "09030109",
      "category": "Gacha",
      "description": "No description provided",
      "icon": "https://play-lh.googleusercontent.com/mR5NzJva7i3xcUZVlk-JlcMIUy04Zx8vUhM5sn94cpX1CA91XjXIrUnxhQGNxNcquEA"
    },
    {
      "name": "OUTERPLANE - Strategy Anime",
      "user_id": "3867131",
      "category": "Gacha",
      "description": "No description provided",
      "icon": "https://play-lh.googleusercontent.com/ur3-7DGSVM-t4HOH56ObNmy43e7KaSDhKHNh9E7l2_k3RhErBopBoA9HTEvTETczQG_2kay9mkZzZ61t4M2L"
    },
    {
      "name": "Bloodstrike",
      "user_id": "586013392269",
      "category": "",
      "description": "No description provided",
      "icon": "https://play-lh.googleusercontent.com/BuBjwtTLhO2bYxYRbvT7a4_jnO32_iPFVDh8LeDLjTvQaS0-aOT9lSSmwPSbcCYMbc0=w240-h480-rw"
    },
    {
      "name": "Onmyoji Arena",
      "user_id": "2308032371",
      "category": "",
      "description": "No description provided",
      "icon": "https://encrypted-tbn0.gstatic.com/images?q=tbn:ANd9GcS9l8fJPDuM9FxS89NKVS8Nf-SKFqRHwdoTuw&s"
    },
    {
      "name": "Honor of Kings",
      "user_id": "11641241486504197650",
      "category": "",
      "description": "What I don't like about this game is the battle rating result is unfair, I like the battle rating result in ML because it based on KDA.",
      "icon": "https://play-lh.googleusercontent.com/hEm5NVeEv7UfFJaK8GZdfWe7p3DB_VvYx57qIEHbR0tMV_NToziH0Vbgd6CxLiWF-iURpAe-jsC_UGUDt0diPQ"
    },
    {
      "name": "Call of Duty Warzone",
      "user_id": "Jaydesu#7620387",
      "category": "",
      "description": "No description provided",
      "icon": "https://play-lh.googleusercontent.com/V5IdturO3h5SiWU6WhyegnUy1rhbwmAI95BO6XbT_9t9I-CCgpqRV-hK4ynPa1tsgg"
    },
    {
      "name": "Wuthering Waves — To Lahai-Roi",
      "user_id": "901728977",
      "category": "Gacha",
      "description": "No description provided",
      "icon": "https://play-lh.googleusercontent.com/Z1Bg75Mp6R91Pjh7argHiyAzB-mXqbL5k4csqppONOPXFe-ga_tjCnQGisPUlAkCOQ9F1njpVjr83Met-yWrMw"
    },
    {
      "name": "Zenless Zone Zero",
      "user_id": "1300474244",
      "category": "Gacha",
      "description": "No description provided",
      "icon": "https://play-lh.googleusercontent.com/8jEmEvTsNIRW1vLlrDXXCcDlKkQrNb8NzccOXrln4G_DOUZpcBPbN9ssjuwBWz7_yZQ",
      "my_gm_rec_img": "/My_Info/Game_Info/My-ZZZ-Info.png",
      "my_gm_rec_link": "https://act.hoyolab.com/app/zzz-game-record/index.html?hyl_presentation_style=fullscreen&bbs_auth_required=true&game_id=8&user_id=71410534&lang=en-us&bbs_theme=dark&bbs_theme_device=1&utm_source=share&utm_medium=link&utm_campaign=web#/zzz"
    },
    {
      "name": "Fate/Grand Order",
      "user_id": "953213672",
      "category": "Gacha",
      "description": "I accidentally delete this game and didn't save this transfer number so GG!",
      "icon": "https://play-lh.googleusercontent.com/WRixOqWRZQHfCgFhqfWbjCh6myA4hO4bOPQ_KJJEKrB_G8KZvl0IvNEUmRuxnfx8Tbw"
    },
    {
      "name": "Strinova",
      "user_id": "2561794",
      "category": [
        "Gacha"
      ],
      "description": "No description provided",
      "icon": "https://encrypted-tbn0.gstatic.com/images?q=tbn:ANd9GcSAvhXyUfA0st1hbfIt41vsvAJ2jZHEsZHTxQ&s"
    },
    {
      "name": "Starseed: Asnia Trigger",
      "user_id": "20000016862",
      "category": "Gacha",
      "description": "No description provided",
      "icon": "https://encrypted-tbn0.gstatic.com/images?q=tbn:ANd9GcRBRsrqwMTqNUDYH4LGifHerrCMmYdEVFU1Aw&s"
    },
    {
      "name": "Heaven Burns Red",
      "user_id": "1753810931247035",
      "category": "Gacha",
      "description": "No description provided",
      "icon": "https://encrypted-tbn0.gstatic.com/images?q=tbn:ANd9GcSVUbU5jNJe2XyMjnk1qXrMQjIvuMbU_yLJmw&s"
    },
    {
      "name": "Girls' Frontline 2: Exilium",
      "user_id": "32479",
      "category": "Gacha",
      "description": "No description provided",
      "icon": "https://encrypted-tbn0.gstatic.com/images?q=tbn:ANd9GcSDVbbuP5xeZdwKVnILl0RlgViaoc4IgCrChQ&s"
    },
    {
      "name": "Infinity Nikki",
      "user_id": "401123008",
      "category": "Gacha",
      "description": "No description provided",
      "icon": "https://encrypted-tbn0.gstatic.com/images?q=tbn:ANd9GcTuP4_1C94RHP0673AJm0LP9DpUigVyD8EIjQ&s"
    },
    {
      "name": "Muse Dash",
      "user_id": "0b3f149aadcc4d2f8b43692e709b38fd",
      "category": [
        "Rhythm",
        "Paid"
      ],
      "description": "No description provided",
      "icon": "https://play-lh.googleusercontent.com/CJpy6_LHwOX93RBdFUvKZ3FG3LR1YXQt_V735QhfMz0TwmpFp415Nit9jBjpDbzBiR-7"
    },
    {
      "name": "Marvel Rivals",
      "user_id": "1094157123",
      "category": "",
      "description": "No description provided",
      "icon": "https://encrypted-tbn0.gstatic.com/images?q=tbn:ANd9GcRjVHXgPFZ-Eywkya07Cl7PPIU0YZaJkTyaDQ&s"
    },
    {
      "name": "Black Beacon",
      "user_id": "25772095530",
      "category": "Gacha",
      "description": "No description provided",
      "icon": "https://play-lh.googleusercontent.com/dnUHxwWxnUlc31BGOHyMeCeG3M6SJ2k_yEYeVuKgVq-pDZ9MKYsxIN3Zc_A6GldR7jGk"
    },
    {
      "name": "MementoMori",
      "user_id": "111561040028",
      "category": "Gacha",
      "description": "No description provided",
      "icon": "https://encrypted-tbn0.gstatic.com/images?q=tbn:ANd9GcSWzq6LKEavHcN8AQWcm-RfpHWDH8dFvkphsA&s"
    },
    {
      "name": "FragPunk",
      "user_id": "3915485788",
      "category": "",
      "description": "No description provided",
      "icon": "https://encrypted-tbn0.gstatic.com/images?q=tbn:ANd9GcQB9F3fkim2n-O9E_upVru4b0jqvbMDMT8wNA&s"
    },
    {
      "name": "BrownDust II",
      "user_id": "16930572",
      "category": "Gacha",
      "description": "No description provided",
      "icon": "https://play-lh.googleusercontent.com/EPBuoNmszDcl_XVvtyzmpjKz4y4NbVdVZZWWS7wpg-5DVqECaDV784hRXhp892145n0=w240-h480-rw"
    },
    {
      "name": "Call of Dragons",
      "user_id": "20317188",
      "category": "",
      "description": "No description provided",
      "icon": "https://play-lh.googleusercontent.com/L7HwAvvMf6wrpHIni1TIqFEipuLRp5_L_UWNCb2FxZkDOFt_YbGNEF6ojc8heXxY1PM"
    },
    {
      "name": "Tribe Nine",
      "user_id": "934460105916",
      "category": "Gacha",
      "description": "No description provided",
      "icon": "https://play-lh.googleusercontent.com/1MkpCk1_GiePh3rDNd7mLiWoLqRzbWRFtRzqeNkT99_KKOtWshNucD8FbSYaBb860Q"
    },
    {
      "name": "Crystal of Atlan",
      "user_id": "23460732",
      "category": "",
      "description": "No description provided",
      "icon": "https://play-lh.googleusercontent.com/rXl0IP9P-kao4sm47DjSsXRROVmlHqBvCkGml0_CgN_5iTtQoRsdDGFpybsVmkaxsQ"
    },
    {
      "name": "Etheria: Restart",
      "user_id": "3049431075144974",
      "category": "Gacha",
      "description": "No description provided",
      "icon": "https://play-lh.googleusercontent.com/lhz9oYEItxn1Hxy1MRMJ6pSnmZgoBaLmvB6MjF9gmbUOpHqLvnMjjtK6KqE_Y8CnOA"
    },
    {
      "name": "Limbus Company",
      "user_id": "F519833212",
      "category": "Gacha",
      "description": "I love the 2D gameplay, my favorite Gameplay on Gacha Game, but why it's only korean voice?",
      "icon": "https://play-lh.googleusercontent.com/qenLAO5zhZNTTKkaRpzJKomp7jqwx_YmDlrmj6Uciqy1rWWWhvCz1u9-lEMmJJ62"
    },
    {
      "name": "Solo Leveling: Arise",
      "user_id": "2GSH5K",
      "category": "Gacha",
      "description": "Alright, my first Male Gacha",
      "icon": "https://cdn2.steamgriddb.com/icon/75d109e54ce75b05064374ae0b77a359.png"
    },
    {
      "name": "Umamusume: Pretty Derby",
      "user_id": "272442827027",
      "category": "Gacha",
      "description": "No description provided",
      "icon": "https://play-lh.googleusercontent.com/yN6cCSP7UB_2bsvlCxrtv-FUpEt1IvEFwr0Ucb3wr39QsAd5PLsueSVXuCinDbE4rifhMlX4YNtpLpkGnpsLhCQ"
    },
    {
      "name": "Lost Sword: Half-Anniversary",
      "user_id": "200292489",
      "category": "Gacha",
      "description": "No description provided",
      "icon": "https://play-lh.googleusercontent.com/zkP4sKdzyTuDgPqa6hZWieC4eHRT3e8MOlwdUnD-OpQSR9ju1P5q7HVpy6rL8HNNLlwIWMCXAnuTso7I9-Sz7I0"
    },
    {
      "name": "Eversoul",
      "user_id": "468721114875",
      "category": "Gacha",
      "description": "No description provided",
      "icon": "https://play-lh.googleusercontent.com/hF8xDpVXNDjM30Oe0czOS7h1Fj710_1c3ahwSZi4SsNo0fO2srcy3vxgkQvfuFMCoN06SNMmM8VdJ2D37A2mQA"
    },
    {
      "name": "P5X | Persona5: The Phantom X",
      "user_id": "55025304082",
      "category": "Gacha",
      "description": "No description provided",
      "icon": "https://play-lh.googleusercontent.com/5dBdKCqdY6uYS5FFcM4Vo4Wpv33enRCT8I7fSYveQI2OBZGnZafeoph2wrbzXJFp1PsAqOwd-uQgVKLqOm_4gA"
    },
    {
      "name": "CounterSide",
      "user_id": "14844958",
      "category": "Gacha",
      "description": "No description provided",
      "icon": "https://play-lh.googleusercontent.com/pwZi0AZuEh2lxfHYRVS-b7YW3zNhrl6TH4I28Rcmz1S57lxTKfgGO_nxsTMGgOswWnvUQ9awc34K9p-Kq-7LYg"
    },
    {
      "name": "AFK Journey",
      "user_id": "52017014",
      "category": "Gacha",
      "description": "No description provided",
      "icon": "https://play-lh.googleusercontent.com/ltX9tk8MFqckmZKmnJnbLhd8aj8B0P-HERsr9fhD4hhQuUfKln-nHFuYDzHwYQm9B-ih_u47Rbr9lhlnfKIXAA"
    },
    {
      "name": "Silver and Blood",
      "user_id": "33872742",
      "category": "Gacha",
      "description": "Nc storytelling but...",
      "icon": "https://play-lh.googleusercontent.com/3FlKHPYNhnJzkkWt-8ZOYhHf3PAoi3L5O6Ndyc3m4FbpQBot_95ITRY3h7NY4SD8O2un"
    },
    {
      "name": "Path to Nowhere",
      "user_id": "562786744667623",
      "category": "Gacha",
      "description": "No description provided",
      "icon": "https://play-lh.googleusercontent.com/9UfTqjBB3QycGGvXIHa_ZoQ5W21GX1jgA2BoNFCERxIsNmnyw7vi2hPDxmwt0krA_IMv1UuOpHZ-_m3sKUkW"
    },
    {
      "name": "ウマ娘 プリティーダービー",
      "user_id": "336925860153",
      "category": "Gacha",
      "description": "My first jp server game, I don't understand kanji but I can still familiarize the GUI is because of the Global Server",
      "icon": "https://play-lh.googleusercontent.com/kpMAHoFE7T_ccji5-P1I6njm7tufDzFHFPTPUDstve1L1_3hKHU29_bu8kZASVSiGOnIpqyG4CmAcib7Kzh8Vg"
    },
    {
      "name": "A Dance of Fire and Ice",
      "user_id": "On steam but I can't find my acc#",
      "category": [
        "Rhythm",
        "Paid"
      ],
      "description": "No description provided",
      "icon": "https://play-lh.googleusercontent.com/L8rCly8hMWuP95PbihDZlSV2u0oGrs0hl2lEXboO7XHX2XalJZ1rjgOsFYXnEDWbpQ"
    },
    {
      "name": "BlasterBeat",
      "user_id": "On steam but I should DL this game first",
      "category": "Rhythm",
      "description": "No description provided",
      "icon": "https://pbs.twimg.com/profile_images/1661658223751856129/x1vp9sVu_400x400.jpg"
    },
    {
      "name": "MuseSwipr",
      "user_id": "On steam but I should DL this game first",
      "category": "Rhythm",
      "description": "No description provided",
      "icon": "https://cdn2.steamgriddb.com/icon_thumb/a2e271a6b5ff067413772cb0bad412a2.png"
    },
    {
      "name": "Project Arrhythmia",
      "user_id": "On steam but I should DL this game first",
      "category": [
        "Rhythm",
        "Paid"
      ],
      "description": "No description provided",
      "icon": "https://encrypted-tbn0.gstatic.com/images?q=tbn:ANd9GcQg4aPNtf6K05-r3tBNjWS1ZjbG0YEy5vuSag&s"
    },
    {
      "name": "Beatblock Demo",
      "user_id": "...",
      "category": "Rhythm",
      "description": "No description provided",
      "icon": "https://img.tapimg.net/market/images/FqKMvPT8XCHYsToYFh2uWwuDFyA1.png"
    },
    {
      "name": "Rhythm Quest Demo",
      "user_id": "...",
      "category": "Rhythm",
      "description": "No description provided",
      "icon": "https://ddrkirby.com/presskit/rhythm-quest/images/logo.png"
    },
    {
      "name": "The Finals",
      "user_id": "On steam but I should DL this game first",
      "category": "",
      "description": "No description provided",
      "icon": "https://sm.ign.com/ign_ap/cover/t/the-finals/the-finals_kbd1.jpg"
    },
    {
      "name": "Helmet Heroes",
      "user_id": "On steam but I should DL this game first",
      "category": "",
      "description": "No description provided",
      "icon": "https://images.sftcdn.net/images/t_app-icon-m/p/82c67df1-a905-4c1c-aade-5bce374f87da/3084267977/helmet-heroes-logo.jpg"
    },
    {
      "name": "Left 4 dead 2",
      "user_id": "On steam but I should get this ID first",
      "category": "Paid",
      "description": "No description provided",
      "icon": "https://encrypted-tbn0.gstatic.com/images?q=tbn:ANd9GcQ06I1fiNRKIvVzQ_FIvDLdVEE2sKCgS3VaEQ&s"
    },
    {
      "name": "Stellar Blade Demo",
      "user_id": "On steam but I should get this ID first",
      "category": "",
      "description": "No description provided",
      "icon": "https://img.tapimg.net/market/images/3c5a9f4a306b68b56f641447b078e2de.jpg"
    },
    {
      "name": "Minecraft: Dream it, Build it!",
      "user_id": "Bought on play store but I should DL this game first",
      "category": "Paid",
      "description": "No description provided",
      "icon": "https://play-lh.googleusercontent.com/27O5tpaYE82W6m30rJ_MX3-UvshlDM6O8oXDxb6GseYW2T7P8UNT19727MGmz-0q3w"
    },
    {
      "name": "Albion Online",
      "user_id": "On steam or play store but I should DL this game first",
      "category": "",
      "description": "No description provided",
      "icon": "https://play-lh.googleusercontent.com/yALXNDwBTVSgYDv4SzKNAc0VB0JVKCxSpkQi7wetdzGhk597aasrnAuN9YNNu3Skns94"
    },
    {
      "name": "Unknown",
      "user_id": "On play store but I should DL this game first",
      "category": "",
      "description": "No description provided",
      "icon": "https://via.placeholder.com/100x100?text=Error",
      "error": "Remote end closed connection without response"
    },
    {
      "name": "Brawlhalla",
      "user_id": "On steam but I should DL this game first",
      "category": "",
      "description": "No description provided",
      "icon": "https://play-lh.googleusercontent.com/np6vjq7-1UEN0rhoO2D5KFWD_u_2ve_od6YzlAUnq2Ty_lR6HBGB-Qsu_E5jS3VI-m5t"
    },
    {
      "name": "Anchor Panic",
      "user_id": "21000531847",
      "category": "Gacha",
      "description": "I give up on this game",
      "icon": "https://play-lh.googleusercontent.com/ZRheW4McuMwcecV3x0_4YLQBixwjz8D5P9vj8d55TsO88QkitB-zshCrmxiaaUD-kRjxbAjmS2-pG0bAoy2OTQ"
    },
    {
      "name": "Seven Knights Re:BIRTH",
      "user_id": "Jaydesuwaa",
      "category": "Gacha",
      "description": "Just search my ID",
      "icon": "https://play-lh.googleusercontent.com/_ocPd2cOaJUvE8cCFsq-co5DBJO6bcAXXmcp6PGyTh9DqIqvo0Tgtx_dnVTz2Edz7MhUJbX7wJcmiPUGxHDG310"
    },
    {
      "name": "Stella Sora",
      "user_id": "700560150",
      "category": "Gacha",
      "description": "No description provided",
      "icon": "https://play-lh.googleusercontent.com/Md-SSbEoGDg3D13E-N_R__nxocrKJzRMSyXuwYVmR0adRsCIWixPvsluzmWjT7LQQQ"
    },
    {
      "name": "Chaos Zero Nightmare",
      "user_id": "435424321410",
      "category": "Gacha",
      "description": "No description provided",
      "icon": "https://play-lh.googleusercontent.com/yJ5g076eKZRCthJPCSOWZYu10Vm_zpJvPwLiGfz7yCCRuI8kiU4LeQWiqcjsga0TyA"
    },
    {
      "name": "Duet Night Abyss",
      "user_id": "6000631192154",
      "category": "Gacha",
      "description": "No description provided",
      "icon": "https://play-lh.googleusercontent.com/JynqYikH08XZ7XgRUzobGY2fIP8T3JwdqseP_y93B7acIy5VSFAHWaRVz-ACFTQACPjJJdmh9fVkJacYwWeNbQ"
    },
    {
      "name": "Trickcal:Chibi Go",
      "user_id": "Jaydesu",
      "category": "Gacha",
      "description": "No description provided",
      "icon": "https://play-lh.googleusercontent.com/UcY_Fu8F_dLCdscwQ2C6l5qG4TiEN72H3GYVS-EEX4OI146EBGrllGLAHOMJpcgpin4"
    },
    {
      "name": "Resonance Solstice",
      "user_id": "5510113708",
      "category": "Gacha",
      "description": "No description provided",
      "icon": "https://play-lh.googleusercontent.com/K5us1fCOXtAy1-U7Mw2gXpZ4SuL5Gvh-TBhza82Y1feFQ3lkInVfCCiWsrb1ysXSVg"
    },
    {
      "name": "Where Winds Meet",
      "user_id": "4013749280",
      "category": "Gacha",
      "description": "No description provided",
      "icon": "https://image.api.playstation.com/vulcan/ap/rnd/202405/2110/070ee110f31b54fa9f18735a3db3f8ccf13b072ad2ce0d9e.png?$100px$"
    },
    {
      "name": "Magic Chess: Go Go",
      "user_id": "On play store but I should DL this game first",
      "category": "",
      "description": "No description provided",
      "icon": "https://play-lh.googleusercontent.com/zpL0shWZobgKXGOYAE1yueyA7RLzY7opF64Jq33sAnB7J5AYtGeQJFs62yTQBNedMJRzZCVe20SqVZvZNe9wxg"
    },
    {
      "name": "Chess - Play and Learn Online",
      "user_id": "On play store but I should DL this game first",
      "category": "",
      "description": "No description provided",
      "icon": "https://play-lh.googleusercontent.com/a7R5nyeaX8lIEWdBOxjlvbyq9LcFwh3XMvNtBPEKR3LPGgdvgGrec4sJwn8tUaaSkw"
    },
    {
      "name": "Fate Trigger",
      "user_id": "302024821",
      "category": "",
      "description": "No description provided",
      "icon": "https://assets-prd.ignimgs.com/2024/09/13/fate-trigger-the-novita-button-1726237557428.jpg?width=300&crop=1%3A1%2Csmart&auto=webp"
    },
    {
      "name": "Mecha BREAK",
      "user_id": "7267805958",
      "category": "",
      "description": "No description provided",
      "icon": "https://images.dwncdn.net/images/t_app-icon-l/p/2089ee34-ca3e-49c9-8122-6ea2867f191c/2245222234/mecha-break-logo"
    },
    {
      "name": "Clair Obscur: Expedition 33",
      "user_id": "...",
      "category": "Steam Family",
      "description": "No description provided",
      "icon": "https://cdn2.steamgriddb.com/grid/d762ffaf700de0c67b2c1af312b53af6.png"
    },
    {
      "name": "Hyperdimension Neptunia Re;Birth1",
      "user_id": "...",
      "category": "Steam Family",
      "description": "No description provided",
      "icon": "https://avatarfiles.alphacoders.com/590/59030.jpg"
    },
    {
      "name": "The NOexistenceN of you AND me",
      "user_id": "...",
      "category": "Steam Family",
      "description": "No description provided",
      "icon": "https://cdn.cloudflare.steamstatic.com/steamcommunity/public/images/items/2873080/82cb5ecf945ecbf96e9509269f19ce3533e0ee93.jpg"
    },
    {
      "name": "REPO",
      "user_id": "...",
      "category": "Steam Family",
      "description": "No description provided",
      "icon": "https://external-preview.redd.it/round-repo-icon-v0-kCGB1sQQkYu42w-2ghQap2d8vU5W1cE9I9fYOzRCw-4.png?auto=webp&s=14e7bc42a8444a10815aa0398e8f334ed78aa8ae"
    },
    {
      "name": "Little Witch Nobeta",
      "user_id": "...",
      "category": "Steam Family",
      "description": "No description provided",
      "icon": "https://www.littlewitchnobeta.com/assets/common/images/character/icon_01_hover.png"
    },
    {
      "name": "Monster Hunter: World",
      "user_id": "...",
      "category": "Steam Family",
      "description": "I played in a short time.",
      "icon": "https://images-wixmp-ed30a86b8c4ca887773594c2.wixmp.com/i/3367fa99-0ba6-454c-b947-683f1a9f896d/ddx6og2-42452595-5cf1-4373-a313-4540833c3c31.png"
    },
    {
      "name": "Borderlands 2",
      "user_id": "...",
      "category": "Steam Family",
      "description": "No description provided",
      "icon": "https://upload.wikimedia.org/wikipedia/en/5/51/Borderlands_2_cover_art.png"
    },
    {
      "name": "Hollow Knight",
      "user_id": "I can't found my ID yet...",
      "category": "Paid",
      "description": "No description provided",
      "icon": "https://i.redd.it/vfnomvstr9g91.jpg"
    },
    {
      "name": "Girls' Frontline: Fire Control",
      "user_id": "67329048",
      "category": "",
      "description": "No description provided",
      "icon": "https://play-lh.googleusercontent.com/-4bF9rw5lS7o5mYPkLzC7s2oVUXXPTMjW3M-xv-9yN3BdFBu5YPUAJvbBLsnKLEiTz77WWXjmycKbW62tl1K5w"
    }
  ]
}